nose2_rp_agent/__init__.py
nose2_reportportal_agent-0.0.1.dist-info/METADATA
nose2_reportportal_agent-0.0.1.dist-info/WHEEL
nose2_reportportal_agent-0.0.1.dist-info/top_level.txt
nose2_reportportal_agent-0.0.1.dist-info/RECORD
